paulaner_colormaps-1.0.0.dist-info/METADATA
paulaner_colormaps-1.0.0.dist-info/WHEEL
paulaner_colormaps-1.0.0.dist-info/LICENSE
paulaner_colormaps/__init__.py
paulaner_colormaps-1.0.0.dist-info/RECORD
