Metadata-Version: 2.1
Name: paulaner_colormaps
Version: 1.0.0
Summary: Paulaner-inspired colormaps
Keywords: paulaner,science,spezi,visualization
Author-Email: Sebastian Stammler <sebastian.stammler@gmail.com>
Maintainer-Email: Sebastian Stammler <sebastian.stammler@gmail.com>
License: BSD 3-Clause License
Classifier: Development Status :: 5 - Production/Stable
Classifier: Intended Audience :: Developers
Classifier: Intended Audience :: Science/Research
Classifier: License :: OSI Approved :: BSD License
Classifier: Natural Language :: English
Classifier: Operating System :: OS Independent
Classifier: Programming Language :: Python
Classifier: Programming Language :: Python :: 3 :: Only
Classifier: Topic :: Education
Classifier: Topic :: Scientific/Engineering
Classifier: Topic :: Scientific/Engineering :: Mathematics
Classifier: Topic :: Scientific/Engineering :: Physics
Classifier: Topic :: Scientific/Engineering :: Visualization
Project-URL: Repository, https://github.com/stammler/paulaner_colormaps/
Requires-Dist: matplotlib
